playneta/__init__.py
playneta/files/codegen/php/server/CoreInterface.php.j2
playneta/files/codegen/php/server/Entrypoint.php.j2
playneta/files/codegen/php/server/RequestHandler.php.j2
playneta/files/codegen/php/server/ResourceInterface.php.j2
playneta/files/codegen/php/server/ResourceWrapper.php.j2
playneta/files/codegen/php/server/index.j2
playneta/files/codegen/php/server/Definition/Object.php.j2
playneta/files/codegen/typescript/client/index.j2
playneta/files/codegen/typescript/client/package.ts.j2
playneta/files/codegen/typescript/server/index.j2
playneta/files/codegen/typescript/server/resource-package.ts.j2
playneta/files/codegen/typescript/server/root-package.ts.j2
playneta/project/__init__.py
playneta/project/build.py
playneta/project/deploy.py
playneta/project/init.py
playneta/project/util.py
playneta/service/__init__.py
playneta/service/target.py
playneta/service/template.py
playneta_cli-0.4.2.dist-info/DESCRIPTION.rst
playneta_cli-0.4.2.dist-info/METADATA
playneta_cli-0.4.2.dist-info/RECORD
playneta_cli-0.4.2.dist-info/WHEEL
playneta_cli-0.4.2.dist-info/entry_points.txt
playneta_cli-0.4.2.dist-info/metadata.json
playneta_cli-0.4.2.dist-info/top_level.txt
